glica/__main__.py
glica-0.4.7.dist-info/LICENSE
glica-0.4.7.dist-info/METADATA
glica-0.4.7.dist-info/WHEEL
glica-0.4.7.dist-info/entry_points.txt
glica-0.4.7.dist-info/top_level.txt
glica-0.4.7.dist-info/RECORD
